download_retry.py
download_retry-0.1.2.dist-info/licenses/LICENSE
download_retry-0.1.2.dist-info/METADATA
download_retry-0.1.2.dist-info/WHEEL
download_retry-0.1.2.dist-info/entry_points.txt
download_retry-0.1.2.dist-info/top_level.txt
download_retry-0.1.2.dist-info/RECORD
