Metadata-Version: 2.4
Name: download-retry
Version: 0.1.2
Summary: Retry downloading a binary file from a URL with timeout and optional SSL check.
Author: Gil Weisbord
License: MIT
Requires-Python: >=3.6
License-File: LICENSE
Requires-Dist: requests>=2.0
Dynamic: license-file
Dynamic: requires-python
